external/__init__.py
external/wavelet.py
kernel/__init__.py
kernel/bins.py
kernel/detectEddies.py
kernel/getScales.py
kernel/io.py
kernel/runAnalysis.py
kernel/spectrum.py
py_altiwaves-0.2.0.post1.data/scripts/test_detection.py
py_altiwaves-0.2.0.post1.data/scripts/test_spectral_analysis.py
py_altiwaves-0.2.0.post1.dist-info/DESCRIPTION.rst
py_altiwaves-0.2.0.post1.dist-info/METADATA
py_altiwaves-0.2.0.post1.dist-info/RECORD
py_altiwaves-0.2.0.post1.dist-info/WHEEL
py_altiwaves-0.2.0.post1.dist-info/metadata.json
py_altiwaves-0.2.0.post1.dist-info/top_level.txt
