Metadata-Version: 2.0
Name: py-altiwaves
Version: 0.2.0.post1
Summary: PyALTIWAVES: Python-based ALong-Track Inventory of WAVelet based EddieS
Home-page: https://code.google.com/p/py-altiwaves/
Author: R. Dussurget
Author-email: renaud.dussurget@gmail.com
License: LICENSE.TXT
Platform: UNKNOWN
Requires-Dist: NetCDF4
Requires-Dist: numpy
Requires-Dist: py-altimetry
